metaspace/__init__.py
metaspace/annotation_export.py
metaspace/dendrogram.py
metaspace/image_processing.py
metaspace/plotting.py
metaspace/projects_client.py
metaspace/sm_annotation_utils.py
metaspace/types.py
metaspace2020-2.0.9.dist-info/LICENSE
metaspace2020-2.0.9.dist-info/METADATA
metaspace2020-2.0.9.dist-info/WHEEL
metaspace2020-2.0.9.dist-info/top_level.txt
metaspace2020-2.0.9.dist-info/RECORD
