Metadata-Version: 2.1
Name: metaspace2020
Version: 2.0.9
Summary: Python library for connecting to the METASPACE platform
Home-page: https://github.com/metaspace2020/metaspace/tree/master/metaspace/python-client
Author: Alexandrov Team, EMBL
Author-email: contact@metaspace2020.eu
License: UNKNOWN
Platform: UNKNOWN
Classifier: Programming Language :: Python :: 3
Classifier: License :: OSI Approved :: Apache Software License
Classifier: Operating System :: OS Independent
Classifier: Topic :: Scientific/Engineering :: Bio-Informatics
Classifier: Intended Audience :: Science/Research
Requires-Dist: matplotlib
Requires-Dist: numpy
Requires-Dist: pandas
Requires-Dist: pillow
Requires-Dist: plotly >=1.12
Requires-Dist: requests
Requires-Dist: tqdm
